qat/linalgutil/linalgutil.so
qat/linalgutil/version.so
qat/linalgutil/wobservable.so
qat_linalg_util-1.0.0.dist-info/licenses/LICENSE.txt
qat_linalg_util-1.0.0.dist-info/METADATA
qat_linalg_util-1.0.0.dist-info/WHEEL
qat_linalg_util-1.0.0.dist-info/top_level.txt
qat_linalg_util-1.0.0.dist-info/RECORD
